pyx/__init__.py
pyx/app.py
pyx/createElement.py
pyx/server.py
pyx/assets/favicon.ico
pyx/assets/index.html
pyx_transpiler/__init__.py
pyx_transpiler/transpile.py
pyx_react-0.1.3.dist-info/LICENSE
pyx_react-0.1.3.dist-info/METADATA
pyx_react-0.1.3.dist-info/WHEEL
pyx_react-0.1.3.dist-info/entry_points.txt
pyx_react-0.1.3.dist-info/top_level.txt
pyx_react-0.1.3.dist-info/RECORD
